session_buddy/__init__.py
session_buddy/__main__.py
session_buddy/acb_cache_adapter.py
session_buddy/advanced_features.py
session_buddy/advanced_search.py
session_buddy/app_monitor.py
session_buddy/cli.py
session_buddy/context_manager.py
session_buddy/crackerjack_integration.py
session_buddy/health_checks.py
session_buddy/interruption_manager.py
session_buddy/knowledge_graph_db.py
session_buddy/llm_providers.py
session_buddy/memory_optimizer.py
session_buddy/multi_project_coordinator.py
session_buddy/natural_scheduler.py
session_buddy/parameter_models.py
session_buddy/quality_engine.py
session_buddy/reflection_tools.py
session_buddy/resource_cleanup.py
session_buddy/search_enhanced.py
session_buddy/server.py
session_buddy/server_core.py
session_buddy/server_optimized.py
session_buddy/serverless_mode.py
session_buddy/session_commands.py
session_buddy/session_types.py
session_buddy/settings.py
session_buddy/shutdown_manager.py
session_buddy/team_knowledge.py
session_buddy/token_optimizer.py
session_buddy/trailing_period_removal_summary.md
session_buddy/types.py
session_buddy/worktree_manager.py
session_buddy/adapters/__init__.py
session_buddy/adapters/knowledge_graph_adapter.py
session_buddy/adapters/knowledge_graph_adapter_oneiric.py
session_buddy/adapters/lifecycle.py
session_buddy/adapters/reflection_adapter.py
session_buddy/adapters/reflection_adapter_oneiric.py
session_buddy/adapters/serverless_storage_adapter.py
session_buddy/adapters/session_storage_adapter.py
session_buddy/adapters/settings.py
session_buddy/adapters/storage_oneiric.py
session_buddy/adapters/storage_registry.py
session_buddy/analytics/__init__.py
session_buddy/analytics/usage_tracker.py
session_buddy/backends/__init__.py
session_buddy/backends/base.py
session_buddy/backends/local_backend.py
session_buddy/backends/redis_backend.py
session_buddy/backends/s3_backend.py
session_buddy/cache/query_cache.py
session_buddy/config/__init__.py
session_buddy/config/feature_flags.py
session_buddy-0.13.0.dist-info/METADATA
session_buddy-0.13.0.dist-info/WHEEL
session_buddy-0.13.0.dist-info/licenses/LICENSE
session_buddy-0.13.0.dist-info/RECORD
