Metadata-Version: 2.4
Name: session-buddy
Version: 0.13.0
Summary: A Session Management MCP Server for Claude Code
Project-URL: documentation, https://github.com/lesleslie/session-buddy
Project-URL: homepage, https://github.com/lesleslie/session-buddy
Project-URL: repository, https://github.com/lesleslie/session-buddy
Author-email: Les Leslie <les@wedgwoodwebworks.com>
License: BSD-3-CLAUSE
License-File: LICENSE
Classifier: Operating System :: POSIX
Classifier: Programming Language :: Python
Classifier: Programming Language :: Python :: 3 :: Only
Classifier: Programming Language :: Python :: 3.13
Classifier: Topic :: Software Development :: Libraries :: Python Modules
Classifier: Typing :: Typed
Requires-Python: >=3.13
Requires-Dist: aiofiles>=25.1.0
Requires-Dist: aiohttp>=3.13.3
Requires-Dist: crackerjack>=0.49.8
Requires-Dist: duckdb>=1.4.3
Requires-Dist: fastmcp>=2.14.4
Requires-Dist: hatchling>=1.28.0
Requires-Dist: numpy>=2.4.1
Requires-Dist: oneiric>=0.3.12
Requires-Dist: onnxruntime>=1.23.2
Requires-Dist: psutil>=7.2.1
Requires-Dist: pydantic>=2.12.5
Requires-Dist: rich>=14.2.0
Requires-Dist: structlog>=25.5.0
Requires-Dist: tiktoken>=0.12.0
Requires-Dist: transformers>=4.57.6
Requires-Dist: typer>=0.21.1
